domaincaller/__init__.py
domaincaller/chromLev.py
domaincaller/genomeLev.py
domaincaller-0.1.0.data/scripts/domaincaller
domaincaller-0.1.0.dist-info/LICENSE
domaincaller-0.1.0.dist-info/METADATA
domaincaller-0.1.0.dist-info/WHEEL
domaincaller-0.1.0.dist-info/top_level.txt
domaincaller-0.1.0.dist-info/RECORD
