Metadata-Version: 2.1
Name: domaincaller
Version: 0.1.0
Summary: A python implementation of original DI-based domain caller proposed by Dixon et al. (2012)
Home-page: https://github.com/XiaoTaoWang/domaincaller/
Author: XiaoTao Wang
Author-email: wangxiaotao686@gmail.com
License: UNKNOWN
Keywords: TAD Hi-C cooler DI
Platform: UNKNOWN
Classifier: Programming Language :: Python
Classifier: License :: OSI Approved :: GNU General Public License v3 or later (GPLv3+)
Classifier: Operating System :: POSIX
Classifier: Development Status :: 3 - Alpha
Classifier: Intended Audience :: Science/Research
Classifier: Topic :: Scientific/Engineering :: Bio-Informatics
